satlaspretrain_models/__init__.py
satlaspretrain_models/model.py
satlaspretrain_models/utils.py
satlaspretrain_models/models/__init__.py
satlaspretrain_models/models/backbones.py
satlaspretrain_models/models/fpn.py
satlaspretrain_models/models/heads.py
satlaspretrain_models-0.3.1.dist-info/LICENSE
satlaspretrain_models-0.3.1.dist-info/METADATA
satlaspretrain_models-0.3.1.dist-info/WHEEL
satlaspretrain_models-0.3.1.dist-info/top_level.txt
satlaspretrain_models-0.3.1.dist-info/RECORD
