Metadata-Version: 2.1
Name: satlaspretrain-models
Version: 0.3.1
Summary: A simple package that makes it easy to load remote sensing foundation models for downstream use cases.
Home-page: https://github.com/allenai/satlaspretrain_models
Author: Satlas @ AI2
Author-email: satlas@allenai.org
License: UNKNOWN
Platform: UNKNOWN
Classifier: Programming Language :: Python :: 3
Classifier: License :: OSI Approved :: Apache Software License
Classifier: Operating System :: OS Independent
Requires-Python: >=3.9
Requires-Dist: torch (>=2.1.0)
Requires-Dist: torchvision (>=0.16.0)
Requires-Dist: requests
Requires-Dist: matplotlib
